{
  "_class": "shapeGroup",
  "clippingMaskMode": 0,
  "do_objectID": "D88CF102-95A7-4FF4-AF23-AA8154428F83",
  "exportOptions": {
    "_class": "exportOptions",
    "do_objectID": "EE340C6A-A422-46DD-8AB1-DB054B67873D",
    "exportFormats": [
    ],
    "includedLayerIds": [
    ],
    "layerOptions": 0,
    "shouldTrim": false
  },
  "frame": {
    "_class": "rect",
    "constrainProportions": false,
    "do_objectID": "0CA5D2C1-9E3F-4170-B644-3F40C93513B5",
    "height": 452,
    "width": 360,
    "x": 0,
    "y": 0
  },
  "hasClickThrough": false,
  "hasClippingMask": false,
  "isFlippedHorizontal": false,
  "isFlippedVertical": false,
  "isLocked": false,
  "isVisible": true,
  "layerListExpandedType": 1,
  "layers": [
    {
      "class": "rectangle",
      "id": "5ACE6EA6-550D-4533-ABF5-3462BE29F6EF"
    },
    {
      "class": "rectangle",
      "id": "20114B84-C432-457F-B417-1522361225CC"
    }
  ],
  "name": "Bg",
  "nameIsFixed": true,
  "resizingConstraint": 63,
  "resizingType": 0,
  "rotation": 0,
  "shouldBreakMaskChain": false,
  "style": {
    "_class": "style",
    "borders": [
      {
        "_class": "border",
        "color": {
          "_class": "color",
          "alpha": 1,
          "blue": 0.592,
          "green": 0.592,
          "red": 0.592
        },
        "fillType": 0,
        "isEnabled": false,
        "position": 1,
        "thickness": 1
      }
    ],
    "do_objectID": "CA7721A3-57EB-48D8-BCA6-9C3B037869DD",
    "endDecorationType": 0,
    "fills": [
      {
        "_class": "fill",
        "color": {
          "_class": "color",
          "alpha": 1,
          "blue": 1,
          "green": 1,
          "red": 1
        },
        "fillType": 0,
        "isEnabled": true,
        "noiseIndex": 0,
        "noiseIntensity": 0,
        "patternFillType": 1,
        "patternTileScale": 1
      }
    ],
    "miterLimit": 10,
    "shadows": [
      {
        "_class": "shadow",
        "blurRadius": 18,
        "color": {
          "_class": "color",
          "alpha": 0.06,
          "blue": 0,
          "green": 0,
          "red": 0
        },
        "contextSettings": {
          "_class": "graphicsContextSettings",
          "blendMode": 0,
          "opacity": 1
        },
        "isEnabled": true,
        "offsetX": 0,
        "offsetY": 10,
        "spread": 0
      }
    ],
    "startDecorationType": 0
  },
  "windingRule": 1
}