{
  "_class": "group",
  "do_objectID": "313293F9-C2C7-44A5-BF3A-FE36228D3EC4",
  "exportOptions": {
    "_class": "exportOptions",
    "exportFormats": [
    ],
    "includedLayerIds": [
    ],
    "layerOptions": 0,
    "shouldTrim": false
  },
  "frame": {
    "_class": "rect",
    "constrainProportions": false,
    "height": 796,
    "width": 470,
    "x": 629,
    "y": 89
  },
  "hasClickThrough": false,
  "isFlippedHorizontal": false,
  "isFlippedVertical": false,
  "isLocked": false,
  "isVisible": true,
  "layerListExpandedType": 0,
  "layers": [
    {
      "class": "group",
      "id": "C6FB26E5-031F-49B2-AAC4-80839E873F47"
    },
    {
      "class": "bitmap",
      "id": "33E4728C-9DCC-4439-8AFA-240F57AF80E1"
    }
  ],
  "name": "Group 3",
  "nameIsFixed": false,
  "resizingConstraint": 63,
  "resizingType": 0,
  "rotation": 0,
  "shouldBreakMaskChain": false,
  "style": {
    "_class": "style",
    "endDecorationType": 0,
    "miterLimit": 10,
    "shadows": [
      {
        "_class": "shadow",
        "blurRadius": 6,
        "color": {
          "_class": "color",
          "alpha": 0.8,
          "blue": 0,
          "green": 0,
          "red": 0
        },
        "contextSettings": {
          "_class": "graphicsContextSettings",
          "blendMode": 0,
          "opacity": 1
        },
        "isEnabled": true,
        "offsetX": 0,
        "offsetY": 7,
        "spread": 0
      }
    ],
    "startDecorationType": 0
  }
}