{
  "_class": "shapePath",
  "booleanOperation": -1,
  "do_objectID": "1439230E-E595-4240-8185-87454654EC06",
  "edited": true,
  "exportOptions": {
    "_class": "exportOptions",
    "exportFormats": [
    ],
    "includedLayerIds": [
    ],
    "layerOptions": 0,
    "shouldTrim": false
  },
  "frame": {
    "_class": "rect",
    "constrainProportions": false,
    "height": 58.9316953125,
    "width": 86.68704873294345,
    "x": 12.09898635477583,
    "y": 3.982183593750001
  },
  "isClosed": true,
  "isFlippedHorizontal": false,
  "isFlippedVertical": false,
  "isLocked": false,
  "isVisible": true,
  "layerListExpandedType": 0,
  "name": "Path",
  "nameIsFixed": false,
  "pointRadiusBehaviour": 1,
  "points": [
    {
      "_class": "curvePoint",
      "cornerRadius": 0,
      "curveFrom": "{1, 0.96690149891485888}",
      "curveMode": 4,
      "curveTo": "{1, 0.9284144766643907}",
      "hasCurveFrom": true,
      "hasCurveTo": false,
      "point": "{1, 0.9284144766643907}"
    },
    {
      "_class": "curvePoint",
      "cornerRadius": 0,
      "curveFrom": "{0.9530216420537716, 1}",
      "curveMode": 4,
      "curveTo": "{0.97911069317571198, 0.99831989020127532}",
      "hasCurveFrom": false,
      "hasCurveTo": true,
      "point": "{0.9530216420537716, 1}"
    },
    {
      "_class": "curvePoint",
      "cornerRadius": 0,
      "curveFrom": "{0.9530216420537716, 0.66546546140480167}",
      "curveMode": 1,
      "curveTo": "{0.9530216420537716, 0.66546546140480167}",
      "hasCurveFrom": false,
      "hasCurveTo": false,
      "point": "{0.9530216420537716, 0.66546546140480167}"
    },
    {
      "_class": "curvePoint",
      "cornerRadius": 0,
      "curveFrom": "{0.9530216420537716, 0.40531550230888325}",
      "curveMode": 1,
      "curveTo": "{0.9530216420537716, 0.40531550230888325}",
      "hasCurveFrom": false,
      "hasCurveTo": false,
      "point": "{0.9530216420537716, 0.40531550230888325}"
    },
    {
      "_class": "curvePoint",
      "cornerRadius": 0,
      "curveFrom": "{0.9530216420537716, 0.22455664708228809}",
      "curveMode": 4,
      "curveTo": "{0.9530216420537716, 0.30137856896563375}",
      "hasCurveFrom": true,
      "hasCurveTo": false,
      "point": "{0.9530216420537716, 0.30137856896563375}"
    },
    {
      "_class": "curvePoint",
      "cornerRadius": 0,
      "curveFrom": "{0.85757101298893801, 0.16206129527338117}",
      "curveMode": 4,
      "curveTo": "{0.91020307954566504, 0.16206129527338117}",
      "hasCurveFrom": false,
      "hasCurveTo": true,
      "point": "{0.85757101298893801, 0.16206129527338117}"
    },
    {
      "_class": "curvePoint",
      "cornerRadius": 0,
      "curveFrom": "{0, 0.16206129527338117}",
      "curveMode": 1,
      "curveTo": "{0, 0.16206129527338117}",
      "hasCurveFrom": false,
      "hasCurveTo": false,
      "point": "{0, 0.16206129527338117}"
    },
    {
      "_class": "curvePoint",
      "cornerRadius": 0,
      "curveFrom": "{0, 0.032185765379596644}",
      "curveMode": 4,
      "curveTo": "{0, 0.071744406958426585}",
      "hasCurveFrom": true,
      "hasCurveTo": false,
      "point": "{0, 0.071744406958426585}"
    },
    {
      "_class": "curvePoint",
      "cornerRadius": 0,
      "curveFrom": "{0.049155533732327832, 0}",
      "curveMode": 4,
      "curveTo": "{0.022052011339843261, 0}",
      "hasCurveFrom": false,
      "hasCurveTo": true,
      "point": "{0.049155533732327832, 0}"
    },
    {
      "_class": "curvePoint",
      "cornerRadius": 0,
      "curveFrom": "{0.97794798866015675, 0}",
      "curveMode": 4,
      "curveTo": "{0.95084446626767216, 0}",
      "hasCurveFrom": true,
      "hasCurveTo": false,
      "point": "{0.95084446626767216, 0}"
    },
    {
      "_class": "curvePoint",
      "cornerRadius": 0,
      "curveFrom": "{1, 0.071744406958426585}",
      "curveMode": 4,
      "curveTo": "{1, 0.032185765379596644}",
      "hasCurveFrom": false,
      "hasCurveTo": true,
      "point": "{1, 0.071744406958426585}"
    }
  ],
  "resizingConstraint": 63,
  "resizingType": 0,
  "rotation": 0,
  "shouldBreakMaskChain": false
}