{
  "_class": "group",
  "do_objectID": "A60E0AD9-69AB-412D-AC68-AB1624AE2A29",
  "exportOptions": {
    "_class": "exportOptions",
    "do_objectID": "211F1F25-F41B-4151-A169-43315D93EF66",
    "exportFormats": [
    ],
    "includedLayerIds": [
    ],
    "layerOptions": 0,
    "shouldTrim": false
  },
  "frame": {
    "_class": "rect",
    "constrainProportions": false,
    "do_objectID": "4C2B2EB0-47DA-47EA-9117-6246732E7832",
    "height": 10,
    "width": 26,
    "x": 12,
    "y": 12
  },
  "hasClickThrough": false,
  "isFlippedHorizontal": false,
  "isFlippedVertical": false,
  "isLocked": false,
  "isVisible": true,
  "layerListExpandedType": 0,
  "layers": [
    {
      "class": "shapeGroup",
      "id": "1ACFAB76-BF9E-4E9C-B44A-9C22EE42A2CA"
    },
    {
      "class": "shapeGroup",
      "id": "D6993A27-2106-4C79-8622-C87D217E867D"
    },
    {
      "class": "shapeGroup",
      "id": "DCC83458-D124-46DD-8B4E-EE77DBA76BAE"
    },
    {
      "class": "shapeGroup",
      "id": "D7E7E4CB-0895-45E9-98C0-6FB812BC5275"
    }
  ],
  "name": "Group",
  "nameIsFixed": false,
  "resizingConstraint": 63,
  "resizingType": 0,
  "rotation": 0,
  "shouldBreakMaskChain": false,
  "style": {
    "_class": "style",
    "blur": {
      "_class": "blur",
      "center": "{0.5, 0.5}",
      "do_objectID": "899FC286-5B09-45CD-A23B-B396AB52CE27",
      "isEnabled": false,
      "motionAngle": 0,
      "radius": 20,
      "type": 0
    },
    "do_objectID": "BB38252C-CB13-4C69-9489-BB0AF599F575",
    "endDecorationType": 0,
    "miterLimit": 10,
    "startDecorationType": 0
  }
}