{
  "_class": "oval",
  "booleanOperation": 1,
  "do_objectID": "54F7914A-5D1D-4557-ADFC-97F35CF7EE84",
  "edited": false,
  "exportOptions": {
    "_class": "exportOptions",
    "do_objectID": "2D2422BC-6B3E-41C1-87EF-B62279B6FA5C",
    "exportFormats": [
    ],
    "includedLayerIds": [
    ],
    "layerOptions": 0,
    "shouldTrim": false
  },
  "frame": {
    "_class": "rect",
    "constrainProportions": false,
    "do_objectID": "A97203C4-DB1B-40A7-9DA4-43D85B47C48A",
    "height": 2321,
    "width": 2321,
    "x": 0,
    "y": 0
  },
  "isClosed": true,
  "isFlippedHorizontal": false,
  "isFlippedVertical": false,
  "isLocked": false,
  "isVisible": true,
  "layerListExpandedType": 0,
  "name": "Oval",
  "nameIsFixed": false,
  "pointRadiusBehaviour": 1,
  "points": [
    {
      "_class": "curvePoint",
      "cornerRadius": 0,
      "curveFrom": "{0.77614237490000004, 1}",
      "curveMode": 2,
      "curveTo": "{0.22385762510000001, 1}",
      "hasCurveFrom": true,
      "hasCurveTo": true,
      "point": "{0.5, 1}"
    },
    {
      "_class": "curvePoint",
      "cornerRadius": 0,
      "curveFrom": "{1, 0.22385762510000001}",
      "curveMode": 2,
      "curveTo": "{1, 0.77614237490000004}",
      "hasCurveFrom": true,
      "hasCurveTo": true,
      "point": "{1, 0.5}"
    },
    {
      "_class": "curvePoint",
      "cornerRadius": 0,
      "curveFrom": "{0.22385762510000001, 0}",
      "curveMode": 2,
      "curveTo": "{0.77614237490000004, 0}",
      "hasCurveFrom": true,
      "hasCurveTo": true,
      "point": "{0.5, 0}"
    },
    {
      "_class": "curvePoint",
      "cornerRadius": 0,
      "curveFrom": "{0, 0.77614237490000004}",
      "curveMode": 2,
      "curveTo": "{0, 0.22385762510000001}",
      "hasCurveFrom": true,
      "hasCurveTo": true,
      "point": "{0, 0.5}"
    }
  ],
  "resizingConstraint": 63,
  "resizingType": 0,
  "rotation": 0,
  "shouldBreakMaskChain": false
}