{
  "_class": "group",
  "do_objectID": "9FB05F7E-A54F-49B6-BA7E-C4309820FB92",
  "exportOptions": {
    "_class": "exportOptions",
    "do_objectID": "4C61F387-32C2-47A3-B173-C2329F00CE37",
    "exportFormats": [
    ],
    "includedLayerIds": [
    ],
    "layerOptions": 0,
    "shouldTrim": false
  },
  "frame": {
    "_class": "rect",
    "constrainProportions": false,
    "do_objectID": "D85F3EB5-9882-432B-AFB3-DBADA16C348D",
    "height": 63,
    "width": 162,
    "x": 165,
    "y": 312
  },
  "hasClickThrough": false,
  "isFlippedHorizontal": false,
  "isFlippedVertical": false,
  "isLocked": false,
  "isVisible": true,
  "layerListExpandedType": 0,
  "layers": [
    {
      "class": "shapeGroup",
      "id": "0BA4CDF3-D60D-423D-B610-02FA44258694"
    },
    {
      "class": "text",
      "id": "1032FFC3-7A33-4B49-92F4-7C1305E1DBDD"
    }
  ],
  "name": "Day 23",
  "nameIsFixed": true,
  "resizingConstraint": 63,
  "resizingType": 0,
  "rotation": 0,
  "shouldBreakMaskChain": false,
  "style": {
    "_class": "style",
    "do_objectID": "4C854E76-9853-432A-B36E-9638011B6DCE",
    "endDecorationType": 0,
    "miterLimit": 10,
    "startDecorationType": 0
  }
}