{
  "_class": "group",
  "do_objectID": "B9B3F952-9415-4274-AD8F-C0F21F1194B9",
  "exportOptions": {
    "_class": "exportOptions",
    "exportFormats": [
    ],
    "includedLayerIds": [
    ],
    "layerOptions": 0,
    "shouldTrim": false
  },
  "frame": {
    "_class": "rect",
    "constrainProportions": false,
    "height": 63,
    "width": 162,
    "x": 2,
    "y": 249
  },
  "hasClickThrough": false,
  "isFlippedHorizontal": false,
  "isFlippedVertical": false,
  "isLocked": false,
  "isVisible": true,
  "layerListExpandedType": 0,
  "layers": [
    {
      "class": "shapeGroup",
      "id": "4C473463-5E17-4334-B061-9E806BEA1572"
    },
    {
      "class": "text",
      "id": "4D34BC56-A00D-4BDF-89D7-24A17D305AD5"
    }
  ],
  "name": "Day 15",
  "nameIsFixed": true,
  "resizingConstraint": 63,
  "resizingType": 0,
  "rotation": 0,
  "shouldBreakMaskChain": false,
  "style": {
    "_class": "style",
    "endDecorationType": 0,
    "miterLimit": 10,
    "startDecorationType": 0
  }
}