{
  "_class": "text",
  "attributedString": {
    "_class": "attributedString",
    "attributes": [
      {
        "_class": "stringAttribute",
        "attributes": {
          "MSAttributedStringColorAttribute": {
            "_class": "color",
            "alpha": 1,
            "blue": 0.5340587496757507,
            "green": 0.5344152450561523,
            "red": 0.5339933633804321
          },
          "MSAttributedStringFontAttribute": {
            "_class": "fontDescriptor",
            "attributes": {
              "name": "Raleway-Regular",
              "size": 16
            }
          },
          "MSTextStyleVerticalAlignment": 0,
          "kerning": 0,
          "paragraphStyle": {
            "_class": "paragraphStyle",
            "alignment": 0,
            "allowsDefaultTighteningForTruncation": 0,
            "maximumLineHeight": 28,
            "minimumLineHeight": 28
          }
        },
        "length": 1729,
        "location": 0
      }
    ],
    "string": "Lorem ipsum dolor sit amet,\n\nconsectetur adipiscing elit, sed do eiusmod tempor incididunt ut labore et dolore magna aliqua. Ut enim ad minim veniam, quis nostrud exercitation ullamco laboris nisi ut aliquip ex ea commodo consequat. nt ut labore et dolore magna aliqua. Ut enim ad minim veniam, quis nostrud exercitation ullamco laboris nisi ut aliquip ex ea commodo consequat.\n\nLorem ipsum dolor sit amet, consectetur adipiscing elit, sed do eiusmod tempor incididunt ut labore et dolore magna aliqua. Ut enim ad minim veniam, quis nostrud exercitation ullamco laboris nisi ut aliquip ex ea commodo consequat.\n\nNt ut labore et dolore magna aliqua. Ut enim ad minim veniam, quis nostrud exercitation ullamco laboris nisi ut aliquip ex ea commodo consequat.Lorem ipsum dolor sit amet, consectetur adipiscing elit, sed do eiusmod tempor incididunt ut labore et dolore magna aliqua. Ut enim ad minim veniam, quis nostrud exercitation ullamco laboris nisi ut aliquip ex ea commodo consequat. Nt ut labore et dolore magna aliqua. \n\nUt enim ad minim veniam, quis nostrud exercitation ullamco laboris nisi ut aliquip ex ea commodo consequat.\n\n\n1. Lorem ipsum dolor sit amet, consectetur adipiscing elit.\n\n2. Sed do eiusmod tempor incididunt ut labore et dolore magna aliqua.\n\n3. Ut enim ad minim veniam, quis nostrud.\n\n4. Nt ut labore et dolore magna aliqua.\n\n5. Ut enim ad minim veniam, quis nostrud exercitation ullamco laboris nisi ut.\n\n6. Aliquip ex ea commodo consequat.Lorem ipsum dolor sit amet.\n\n\nLorem ipsum dolor sit amet, consectetur adipiscing elit, sed do eiusmod tempor incididunt ut labore et dolore magna aliqua. Ut enim ad minim veniam, quis nostrud exercitation ullamco laboris nisi ut aliquip ex ea commodo consequat."
  },
  "automaticallyDrawOnUnderlyingPath": false,
  "do_objectID": "513711DC-0CF2-4DA7-AE54-44D3CA60A143",
  "dontSynchroniseWithSymbol": false,
  "exportOptions": {
    "_class": "exportOptions",
    "do_objectID": "3F7EF10B-C90C-47C8-B7ED-7B1A62270B81",
    "exportFormats": [
    ],
    "includedLayerIds": [
    ],
    "layerOptions": 0,
    "shouldTrim": false
  },
  "frame": {
    "_class": "rect",
    "constrainProportions": false,
    "do_objectID": "6C6998D5-EC67-452B-94D7-A1B7F5730244",
    "height": 980,
    "width": 848,
    "x": 682,
    "y": 347
  },
  "glyphBounds": "{{0, 8}, {840, 968}}",
  "isFlippedHorizontal": false,
  "isFlippedVertical": false,
  "isLocked": false,
  "isVisible": true,
  "layerListExpandedType": 0,
  "lineSpacingBehaviour": 2,
  "name": "Text",
  "nameIsFixed": true,
  "resizingConstraint": 63,
  "resizingType": 0,
  "rotation": 0,
  "shouldBreakMaskChain": false,
  "style": {
    "sharedObjectID": "D0BB3CD6-1D2E-4B72-ABD1-0BF07E0A7102"
  },
  "textBehaviour": 1
}