{
  "_class": "group",
  "do_objectID": "6652BA56-3838-4B56-8AE0-4773764066AE",
  "exportOptions": {
    "_class": "exportOptions",
    "exportFormats": [
    ],
    "includedLayerIds": [
    ],
    "layerOptions": 0,
    "shouldTrim": false
  },
  "frame": {
    "_class": "rect",
    "constrainProportions": false,
    "height": 440,
    "width": 1433,
    "x": 244,
    "y": 1763
  },
  "hasClickThrough": false,
  "isFlippedHorizontal": false,
  "isFlippedVertical": false,
  "isLocked": false,
  "isVisible": true,
  "layerListExpandedType": 0,
  "layers": [
    {
      "class": "group",
      "id": "BC097A16-9A52-442C-873E-552D0927C394"
    },
    {
      "class": "group",
      "id": "C461D5C6-659A-46E5-B0C6-70D48BA6352D"
    }
  ],
  "name": "Group 8",
  "nameIsFixed": false,
  "resizingConstraint": 63,
  "resizingType": 0,
  "rotation": 0,
  "shouldBreakMaskChain": false,
  "style": {
    "_class": "style",
    "endDecorationType": 0,
    "miterLimit": 10,
    "startDecorationType": 0
  }
}