{
  "_class": "symbolInstance",
  "do_objectID": "8F19266D-A851-4FFC-9601-4A0D7D75A2FF",
  "exportOptions": {
    "_class": "exportOptions",
    "do_objectID": "DB0156C3-6FEA-48CF-9ECD-4BC2CF247D33",
    "exportFormats": [
    ],
    "includedLayerIds": [
    ],
    "layerOptions": 0,
    "shouldTrim": false
  },
  "frame": {
    "_class": "rect",
    "constrainProportions": false,
    "do_objectID": "D6C8B6C1-B20D-49BE-99E4-BDB5825B01AA",
    "height": 50,
    "width": 160,
    "x": 0,
    "y": 0
  },
  "horizontalSpacing": 0,
  "isFlippedHorizontal": false,
  "isFlippedVertical": false,
  "isLocked": false,
  "isVisible": true,
  "layerListExpandedType": 0,
  "name": "Filled Button (color)",
  "nameIsFixed": false,
  "overrideValues": [
    {
      "_class": "overrideValue",
      "do_objectID": "E96CB836-5BFC-4EB3-8061-783DC8DB21A9",
      "overrideName": "E4D13818-0E84-400C-B4F1-ED4F18A26F7E_stringValue",
      "value": "Registrarme"
    }
  ],
  "resizingConstraint": 63,
  "resizingType": 0,
  "rotation": 0,
  "scale": 1,
  "shouldBreakMaskChain": false,
  "style": {
    "_class": "style",
    "do_objectID": "5C77B633-75EA-460B-8558-7CEADA5B5C28",
    "endDecorationType": 0,
    "miterLimit": 10,
    "startDecorationType": 0
  },
  "symbolID": "54ECC998-F950-468D-B34D-D7C5E6E2574F",
  "verticalSpacing": 0
}