{
  "_class": "symbolInstance",
  "do_objectID": "9C641479-F01F-45D6-B26F-82664FB7F467",
  "exportOptions": {
    "_class": "exportOptions",
    "do_objectID": "39E8C476-BB80-4031-9C8C-E6B3E12EDD9F",
    "exportFormats": [
    ],
    "includedLayerIds": [
    ],
    "layerOptions": 0,
    "shouldTrim": false
  },
  "frame": {
    "_class": "rect",
    "constrainProportions": false,
    "do_objectID": "0CE7D0E2-0050-4BCF-8F93-A34D67C6BC45",
    "height": 50,
    "width": 310,
    "x": 0,
    "y": 0
  },
  "horizontalSpacing": 0,
  "isFlippedHorizontal": false,
  "isFlippedVertical": false,
  "isLocked": false,
  "isVisible": true,
  "layerListExpandedType": 0,
  "name": "Go Button",
  "nameIsFixed": false,
  "overrideValues": [
  ],
  "resizingConstraint": 63,
  "resizingType": 0,
  "rotation": 0,
  "scale": 1,
  "shouldBreakMaskChain": false,
  "style": {
    "_class": "style",
    "do_objectID": "542A28D8-57A5-4678-AA92-A58F3492B2C7",
    "endDecorationType": 0,
    "miterLimit": 10,
    "startDecorationType": 0
  },
  "symbolID": "2CF397A9-19B4-4722-B75E-AB89C5D437E3",
  "verticalSpacing": 0
}