{
  "_class": "shapePath",
  "booleanOperation": -1,
  "do_objectID": "276FF433-7398-4141-97FE-5F96FDEBC486",
  "edited": true,
  "exportOptions": {
    "_class": "exportOptions",
    "do_objectID": "9E5AA6F2-A79A-4590-88AE-7A6FDB9387A3",
    "exportFormats": [
    ],
    "includedLayerIds": [
    ],
    "layerOptions": 0,
    "shouldTrim": false
  },
  "frame": {
    "_class": "rect",
    "constrainProportions": false,
    "do_objectID": "7B313D27-B723-41B5-8CD7-6D34C95E10C2",
    "height": 8.958459642704637,
    "width": 10.95821692008183,
    "x": 43.86787362751274,
    "y": 4.058412534570126
  },
  "isClosed": false,
  "isFlippedHorizontal": false,
  "isFlippedVertical": false,
  "isLocked": false,
  "isVisible": true,
  "layerListExpandedType": 0,
  "name": "Path",
  "nameIsFixed": false,
  "pointRadiusBehaviour": 0,
  "points": [
    {
      "_class": "curvePoint",
      "cornerRadius": 0,
      "curveFrom": "{0.96446967467086975, 0.023231365628842513}",
      "curveMode": 1,
      "curveTo": "{0.96446967467086975, 0.023231365628842513}",
      "hasCurveFrom": false,
      "hasCurveTo": false,
      "point": "{0.96446967467086975, 0.023231365628842513}"
    },
    {
      "_class": "curvePoint",
      "cornerRadius": 0,
      "curveFrom": "{0.74307220956067777, 0.023231365628842513}",
      "curveMode": 4,
      "curveTo": "{0.76052745809880773, 0.023231365628842513}",
      "hasCurveFrom": true,
      "hasCurveTo": false,
      "point": "{0.76052745809880773, 0.023231365628842513}"
    },
    {
      "_class": "curvePoint",
      "cornerRadius": 0,
      "curveFrom": "{0.72543837084622254, 0.059472296009836827}",
      "curveMode": 4,
      "curveTo": "{0.7281871066035619, 0.038559373738700886}",
      "hasCurveFrom": false,
      "hasCurveTo": true,
      "point": "{0.72543837084622254, 0.059472296009836827}"
    },
    {
      "_class": "curvePoint",
      "cornerRadius": 0,
      "curveFrom": "{0.71649333244945868, 0.12837793442653722}",
      "curveMode": 1,
      "curveTo": "{0.71649333244945868, 0.12837793442653722}",
      "hasCurveFrom": false,
      "hasCurveTo": false,
      "point": "{0.71649333244945868, 0.12837793442653722}"
    },
    {
      "_class": "curvePoint",
      "cornerRadius": 0,
      "curveFrom": "{0.65806328563031669, 0.025953424631817931}",
      "curveMode": 4,
      "curveTo": "{0.70221388313379018, 0.10341946929235855}",
      "hasCurveFrom": true,
      "hasCurveTo": false,
      "point": "{0.70221388313379018, 0.10341946929235855}"
    },
    {
      "_class": "curvePoint",
      "cornerRadius": 0,
      "curveFrom": "{0.23601587502464852, 0}",
      "curveMode": 3,
      "curveTo": "{0.55961350973398338, 0}",
      "hasCurveFrom": true,
      "hasCurveTo": true,
      "point": "{0.46131902964315025, 0}"
    },
    {
      "_class": "curvePoint",
      "cornerRadius": 0,
      "curveFrom": "{-0.013389188607357496, 0.64035968724480707}",
      "curveMode": 3,
      "curveTo": "{0.04355778326926512, 0.20643532293944827}",
      "hasCurveFrom": true,
      "hasCurveTo": true,
      "point": "{0.006108199773089542, 0.4959122182903592}"
    },
    {
      "_class": "curvePoint",
      "cornerRadius": 0,
      "curveFrom": "{0.14425934834533916, 0.96315833935628015}",
      "curveMode": 2,
      "curveTo": "{0.014284523932631934, 0.77835869228530929}",
      "hasCurveFrom": true,
      "hasCurveTo": true,
      "point": "{0.082047848662286663, 0.87467264893886654}"
    },
    {
      "_class": "curvePoint",
      "cornerRadius": 0,
      "curveFrom": "{0.52051002590923967, 1}",
      "curveMode": 3,
      "curveTo": "{0.23305748992988554, 1}",
      "hasCurveFrom": true,
      "hasCurveTo": true,
      "point": "{0.33886828700688842, 1}"
    },
    {
      "_class": "curvePoint",
      "cornerRadius": 0,
      "curveFrom": "{0.62121935577558851, 0.85900673005622474}",
      "curveMode": 4,
      "curveTo": "{0.62121935577558851, 0.85900673005622474}",
      "hasCurveFrom": false,
      "hasCurveTo": true,
      "point": "{0.62121935577558851, 0.85900673005622474}"
    },
    {
      "_class": "curvePoint",
      "cornerRadius": 0,
      "curveFrom": "{0.60870251385233776, 0.95352788233195984}",
      "curveMode": 4,
      "curveTo": "{0.61210349199277414, 0.92750875282765621}",
      "hasCurveFrom": true,
      "hasCurveTo": false,
      "point": "{0.61210349199277414, 0.92750875282765621}"
    },
    {
      "_class": "curvePoint",
      "cornerRadius": 0,
      "curveFrom": "{0.64719257924535933, 0.97709715873358549}",
      "curveMode": 4,
      "curveTo": "{0.62534245941159672, 0.97709715873358549}",
      "hasCurveFrom": false,
      "hasCurveTo": true,
      "point": "{0.64719257924535933, 0.97709715873358549}"
    },
    {
      "_class": "curvePoint",
      "cornerRadius": 0,
      "curveFrom": "{0.85997112715033641, 0.97709715873358549}",
      "curveMode": 4,
      "curveTo": "{0.83081433966782769, 0.97709715873358549}",
      "hasCurveFrom": true,
      "hasCurveTo": false,
      "point": "{0.83081433966782769, 0.97709715873358549}"
    },
    {
      "_class": "curvePoint",
      "cornerRadius": 0,
      "curveFrom": "{0.88929874001889486, 0.91676131297108054}",
      "curveMode": 4,
      "curveTo": "{0.88474080812748812, 0.95153796333668128}",
      "hasCurveFrom": false,
      "hasCurveTo": true,
      "point": "{0.88929874001889486, 0.91676131297108054}"
    },
    {
      "_class": "curvePoint",
      "cornerRadius": 0,
      "curveFrom": "{1.0029597400638912, 0.046791255620113069}",
      "curveMode": 4,
      "curveTo": "{0.99955876192345494, 0.072819771534771802}",
      "hasCurveFrom": true,
      "hasCurveTo": false,
      "point": "{0.99955876192345494, 0.072819771534771802}"
    },
    {
      "_class": "curvePoint",
      "cornerRadius": 0,
      "curveFrom": "{0.96446967467086975, 0.023231365628842513}",
      "curveMode": 4,
      "curveTo": "{0.98626544097270796, 0.023231365628842513}",
      "hasCurveFrom": false,
      "hasCurveTo": true,
      "point": "{0.96446967467086975, 0.023231365628842513}"
    }
  ],
  "resizingConstraint": 63,
  "resizingType": 0,
  "rotation": 0,
  "shouldBreakMaskChain": false
}