{
  "_class": "group",
  "do_objectID": "B7E1E683-361E-4379-BA7C-870FD01C1C8C",
  "exportOptions": {
    "_class": "exportOptions",
    "do_objectID": "C56EC3F9-6647-4241-81A3-D7D3EBA9C4C5",
    "exportFormats": [
    ],
    "includedLayerIds": [
    ],
    "layerOptions": 0,
    "shouldTrim": false
  },
  "frame": {
    "_class": "rect",
    "constrainProportions": false,
    "do_objectID": "2D387F26-4EF1-43BD-842A-79605D9769F3",
    "height": 384,
    "width": 890,
    "x": 0,
    "y": 0
  },
  "hasClickThrough": false,
  "isFlippedHorizontal": false,
  "isFlippedVertical": false,
  "isLocked": false,
  "isVisible": true,
  "layerListExpandedType": 0,
  "layers": [
    {
      "class": "shapeGroup",
      "id": "5787FF63-5776-4CDC-B2AE-3A96D4E5F662"
    },
    {
      "class": "shapeGroup",
      "id": "97B2464B-AFE8-4A3A-8C8C-B4141AB16D45"
    },
    {
      "class": "group",
      "id": "3E649DFF-4D65-4D6D-AE85-A4928C57091A"
    },
    {
      "class": "group",
      "id": "5FB04668-8CE0-4955-9A45-55778E1E28A6"
    },
    {
      "class": "group",
      "id": "083A5F28-9236-4464-98B3-6A3F392C036A"
    },
    {
      "class": "group",
      "id": "F2DD2E6A-FF6E-4990-86E8-EEC1ABF29752"
    },
    {
      "class": "group",
      "id": "15ECBEE2-B03D-4EE8-81E3-1F35128BDCF5"
    },
    {
      "class": "group",
      "id": "CD047E6B-3C38-41C5-8B73-1022000CAB4A"
    }
  ],
  "name": "only pick up",
  "nameIsFixed": true,
  "resizingConstraint": 63,
  "resizingType": 0,
  "rotation": 0,
  "shouldBreakMaskChain": false,
  "style": {
    "_class": "style",
    "do_objectID": "EAC34467-1374-4BE7-92C1-416F3CFA40EE",
    "endDecorationType": 0,
    "miterLimit": 10,
    "startDecorationType": 0
  }
}