{
  "_class": "group",
  "do_objectID": "FC54539E-FDD3-4638-A139-FB6D72A42787",
  "exportOptions": {
    "_class": "exportOptions",
    "exportFormats": [
    ],
    "includedLayerIds": [
    ],
    "layerOptions": 0,
    "shouldTrim": false
  },
  "frame": {
    "_class": "rect",
    "constrainProportions": false,
    "height": 24,
    "width": 87,
    "x": 195,
    "y": 57
  },
  "hasClickThrough": false,
  "isFlippedHorizontal": false,
  "isFlippedVertical": false,
  "isLocked": false,
  "isVisible": true,
  "layerListExpandedType": 2,
  "layers": [
    {
      "class": "text",
      "id": "4CEC0807-42D3-4637-975B-B85664FA932A"
    },
    {
      "class": "group",
      "id": "F183391E-C1B8-4830-ACA9-F5A3D6A52791"
    }
  ],
  "name": "Gear",
  "nameIsFixed": true,
  "resizingConstraint": 63,
  "resizingType": 0,
  "rotation": 0,
  "shouldBreakMaskChain": false,
  "style": {
    "_class": "style",
    "endDecorationType": 0,
    "miterLimit": 10,
    "startDecorationType": 0
  }
}